qb_runtime/__init__.py
qb_runtime/functions.py
qb_runtime/types.py
qb_runtime/wrappers.py
qb_runtime-0.1.1.dist-info/METADATA
qb_runtime-0.1.1.dist-info/WHEEL
qb_runtime-0.1.1.dist-info/RECORD
