Metadata-Version: 2.3
Name: qb-runtime
Version: 0.1.1
Summary: The qb runtime, developed separately from the qb compiler for more flexibility.
Author: henceiusegentoo
Author-email: 61363222+henceiusegentoo@users.noreply.github.com
Requires-Python: >=3.13
Classifier: Programming Language :: Python :: 3
Classifier: Programming Language :: Python :: 3.13
